codepy/__init__.py
codepy/cache.py
codepy/commands.py
codepy/core.py
codepy/events.py
codepy/ia.py
codepy/interactions.py
codepy/metrics.py
codepy/oauth.py
codepy/tipos.py
codepy/utils.py
codepy/voice.py
codepy/webhook.py
tests/__init__.py
tests/test_commands.py
tests/test_core.py
tests/test_oauth.py
codepy_redebots-1.0.0.dist-info/METADATA
codepy_redebots-1.0.0.dist-info/WHEEL
codepy_redebots-1.0.0.dist-info/top_level.txt
codepy_redebots-1.0.0.dist-info/RECORD
