Metadata-Version: 2.4
Name: codepy-redebots
Version: 1.0.0
Summary: Biblioteca pioneira para bots Discord 2025, 100% brasileira, com suporte a IA, voz, OAuth2 e interações modernas.
Home-page: https://github.com/LucasDesignerF/code-py
Author: Lucas Dev - RedeBots
Author-email: ofc.rede@gmail.com
Classifier: Programming Language :: Python :: 3
Classifier: License :: OSI Approved :: MIT License
Classifier: Operating System :: OS Independent
Requires-Python: >=3.12.7
Requires-Dist: aiohttp>=3.11.17
Requires-Dist: redis>=5.2.1
Dynamic: author
Dynamic: author-email
Dynamic: classifier
Dynamic: description
Dynamic: description-content-type
Dynamic: home-page
Dynamic: requires-dist
Dynamic: requires-python
Dynamic: summary
